brahmastra/__init__.py
brahmastra/brahmastra.py
brahmastra-0.1.0.dist-info/LICENSE
brahmastra-0.1.0.dist-info/METADATA
brahmastra-0.1.0.dist-info/WHEEL
brahmastra-0.1.0.dist-info/top_level.txt
brahmastra-0.1.0.dist-info/RECORD
