Metadata-Version: 2.1
Name: brahmastra
Version: 0.1.0
Summary: The Brahmastra is an undetected WebDriver, inspired by the legendary weapon of unparalleled power and destruction. Just like its mythical namesake, this tool is designed to be a formidable asset in your automation arsenal. It allows you to navigate any website or webpage effortlessly and invisibly, bypassing anti-bot measures with ease. With Brahmastra, automating your web tasks becomes seamless and worry-free, making it an indispensable tool for developers and automation enthusiasts al
Home-page: https://github.com/nnishad/brahmastra
Author: Nikhil Nishad
Author-email: nikhil.nishad@outlook.in
Classifier: Programming Language :: Python :: 3
Classifier: License :: OSI Approved :: MIT License
Classifier: Operating System :: OS Independent
Requires-Python: >=3.6
License-File: LICENSE
Requires-Dist: undetected-chromedriver
Requires-Dist: fake-useragent
